workflow_use/__init__.py
workflow_use/builder/prompts.py
workflow_use/builder/service.py
workflow_use/builder/tests/build_workflow.py
workflow_use/controller/service.py
workflow_use/controller/utils.py
workflow_use/controller/views.py
workflow_use/healing/deterministic_converter.py
workflow_use/healing/prompts.py
workflow_use/healing/selector_generator.py
workflow_use/healing/service.py
workflow_use/healing/validator.py
workflow_use/healing/variable_extractor.py
workflow_use/healing/variable_utils.py
workflow_use/healing/views.py
workflow_use/healing/_agent/agent_prompt.md
workflow_use/healing/_agent/controller.py
workflow_use/healing/prompts/workflow_creation_prompt.md
workflow_use/healing/prompts/workflow_validation_prompt.md
workflow_use/healing/tests/constants.py
workflow_use/healing/tests/test_exploration_agent.py
workflow_use/healing/tests/test_generate_workflow.py
workflow_use/healing/tests/test_validator.py
workflow_use/healing/tests/test_variable_extractor.py
workflow_use/healing/tests/test_workflow_creation.py
workflow_use/mcp/service.py
workflow_use/mcp/tests/test_tools.py
workflow_use/recorder/recorder.py
workflow_use/recorder/semantic_converter.py
workflow_use/recorder/service.py
workflow_use/recorder/views.py
workflow_use/schema/views.py
workflow_use/storage/__init__.py
workflow_use/storage/service.py
workflow_use/workflow/element_finder.py
workflow_use/workflow/error_reporter.py
workflow_use/workflow/prompts.py
workflow_use/workflow/semantic_executor.py
workflow_use/workflow/semantic_extractor.py
workflow_use/workflow/service.py
workflow_use/workflow/step_verifier.py
workflow_use/workflow/validation_utils.py
workflow_use/workflow/variable_config.py
workflow_use/workflow/variable_identifier.py
workflow_use/workflow/views.py
workflow_use/workflow/prompts/agent_step_system_prompt.md
workflow_use/workflow/step_agent/controller.py
workflow_use/workflow/tests/run_workflow.py
workflow_use/workflow/tests/run_workflow_tool.py
workflow_use-0.2.9.dist-info/METADATA
workflow_use-0.2.9.dist-info/WHEEL
workflow_use-0.2.9.dist-info/RECORD
