Metadata-Version: 2.4
Name: workflow-use
Version: 0.2.9
Summary: Create, edit, run deterministic workflows
Author: Gregor Zunic
Classifier: License :: OSI Approved
Classifier: Operating System :: OS Independent
Classifier: Programming Language :: Python :: 3
Requires-Python: >=3.11
Requires-Dist: aiofiles>=24.1.0
Requires-Dist: browser-use>=0.9.4
Requires-Dist: faiss-cpu==1.10.0
Requires-Dist: fastapi>=0.115.12
Requires-Dist: fastmcp>=2.3.4
Requires-Dist: markdownify>=0.11.6
Requires-Dist: pandas>=2.3.0
Requires-Dist: pyyaml>=6.0.0
Requires-Dist: typer>=0.15.3
Requires-Dist: uvicorn>=0.34.2
